polynomial2d/__init__.py
polynomial2d/polynomial2d.py
polynomial2d-4.2.5.dist-info/LICENSE
polynomial2d-4.2.5.dist-info/METADATA
polynomial2d-4.2.5.dist-info/WHEEL
polynomial2d-4.2.5.dist-info/top_level.txt
polynomial2d-4.2.5.dist-info/RECORD
