Metadata-Version: 2.1
Name: polynomial2d
Version: 4.2.5
Summary: UNKNOWN
Home-page: https://github.com/bkornpob/polynomial2d
Author: Kornpob Bhirombhakdi
Author-email: kbhirombhakdi@stsci.edu
License: UNKNOWN
Platform: UNKNOWN
Classifier: Programming Language :: Python :: 3
Classifier: License :: OSI Approved :: MIT License
Classifier: Operating System :: OS Independent
Requires-Python: >=3
